{
   "graph": {
      "yAxis": {
         "maxValue": 55,
         "minValue": 15
      },
      "datasequences": [
         {
            "color": "red",
            "datapoints": [
               {
                  "title": "02:20",
                  "value": "25.92"
               },
               {
                  "title": "02:20",
                  "value": "25.88"
               },
               {
                  "title": "02:30",
                  "value": "25.94"
               },
               {
                  "title": "02:30",
                  "value": "25.92"
               },
               {
                  "title": "02:40",
                  "value": "25.86"
               },
               {
                  "title": "02:50",
                  "value": "25.95"
               },
               {
                  "title": "03:00",
                  "value": "26.02"
               },
               {
                  "title": "03:10",
                  "value": "25.95"
               },
               {
                  "title": "03:20",
                  "value": "25.92"
               },
               {
                  "title": "03:20",
                  "value": "25.92"
               },
               {
                  "title": "03:30",
                  "value": "25.89"
               },
               {
                  "title": "03:30",
                  "value": "25.89"
               }
            ],
            "title": "Temperatura"
         },
         {
            "color": "blue",
            "datapoints": [
               {
                  "title": "02:20",
                  "value": "941.96"
               },
               {
                  "title": "02:20",
                  "value": "941.93"
               },
               {
                  "title": "02:30",
                  "value": "941.83"
               },
               {
                  "title": "02:30",
                  "value": "941.85"
               },
               {
                  "title": "02:40",
                  "value": "941.78"
               },
               {
                  "title": "02:50",
                  "value": "941.68"
               },
               {
                  "title": "03:00",
                  "value": "941.62"
               },
               {
                  "title": "03:10",
                  "value": "941.55"
               },
               {
                  "title": "03:20",
                  "value": "941.57"
               },
               {
                  "title": "03:20",
                  "value": "941.57"
               },
               {
                  "title": "03:30",
                  "value": "941.51"
               },
               {
                  "title": "03:30",
                  "value": "941.53"
               }
            ],
            "title": "Presion"
         }
      ],
      "type": "line",
      "title": "Balcon"
   }
}