{
   "graph": {
      "yAxis": {
         "maxValue": 55,
         "minValue": 15
      },
      "datasequences": [
         {
            "color": "red",
            "datapoints": [
               {
                  "title": "19:50",
                  "value": "28.01"
               },
               {
                  "title": "19:50",
                  "value": "28.0"
               },
               {
                  "title": "20:00",
                  "value": "28.0"
               },
               {
                  "title": "20:00",
                  "value": "27.96"
               },
               {
                  "title": "20:10",
                  "value": "27.71"
               },
               {
                  "title": "20:20",
                  "value": "27.49"
               },
               {
                  "title": "20:30",
                  "value": "27.37"
               },
               {
                  "title": "20:40",
                  "value": "27.14"
               },
               {
                  "title": "20:50",
                  "value": "26.81"
               },
               {
                  "title": "21:00",
                  "value": "26.6"
               },
               {
                  "title": "21:10",
                  "value": "26.42"
               },
               {
                  "title": "21:20",
                  "value": "26.03"
               }
            ],
            "title": "Temperatura"
         },
         {
            "color": "blue",
            "datapoints": [
               {
                  "title": "19:30",
                  "value": "942.41"
               },
               {
                  "title": "19:40",
                  "value": "942.62"
               },
               {
                  "title": "19:50",
                  "value": "942.83"
               },
               {
                  "title": "20:00",
                  "value": "942.98"
               },
               {
                  "title": "20:10",
                  "value": "943.08"
               },
               {
                  "title": "20:20",
                  "value": "943.37"
               },
               {
                  "title": "20:30",
                  "value": "943.54"
               },
               {
                  "title": "20:40",
                  "value": "943.64"
               },
               {
                  "title": "20:50",
                  "value": "943.79"
               },
               {
                  "title": "21:00",
                  "value": "943.83"
               },
               {
                  "title": "21:10",
                  "value": "943.97"
               },
               {
                  "title": "21:20",
                  "value": "944.14"
               }
            ],
            "title": "Presion"
         }
      ],
      "type": "line",
      "title": "Balcon"
   }
}