{
   "graph": {
      "title": "Living",
      "datasequences": [
         {
            "color": "red",
            "title": "Temperatura",
            "datapoints": [
               {
                  "value": "27.5",
                  "title": "11:50"
               },
               {
                  "value": "27.5",
                  "title": "11:50"
               },
               {
                  "value": "27.5",
                  "title": "12:00"
               },
               {
                  "value": "27.5",
                  "title": "12:00"
               },
               {
                  "value": "27.7",
                  "title": "12:10"
               },
               {
                  "value": "27.7",
                  "title": "12:10"
               },
               {
                  "value": "27.9",
                  "title": "12:20"
               },
               {
                  "value": "27.9",
                  "title": "12:20"
               },
               {
                  "value": "27.9",
                  "title": "12:30"
               },
               {
                  "value": "27.9",
                  "title": "12:30"
               },
               {
                  "value": "28.0",
                  "title": "12:40"
               },
               {
                  "value": "28.0",
                  "title": "12:40"
               }
            ]
         },
         {
            "color": "blue",
            "title": "Humedad",
            "datapoints": [
               {
                  "value": "29.9",
                  "title": "11:50"
               },
               {
                  "value": "30.0",
                  "title": "11:50"
               },
               {
                  "value": "29.7",
                  "title": "12:00"
               },
               {
                  "value": "30.0",
                  "title": "12:00"
               },
               {
                  "value": "30.7",
                  "title": "12:10"
               },
               {
                  "value": "30.6",
                  "title": "12:10"
               },
               {
                  "value": "29.6",
                  "title": "12:20"
               },
               {
                  "value": "29.5",
                  "title": "12:20"
               },
               {
                  "value": "29.6",
                  "title": "12:30"
               },
               {
                  "value": "29.6",
                  "title": "12:30"
               },
               {
                  "value": "29.5",
                  "title": "12:40"
               },
               {
                  "value": "29.5",
                  "title": "12:40"
               }
            ]
         }
      ],
      "type": "line",
      "yAxis": {
         "maxValue": 55,
         "minValue": 15
      }
   }
}