{
   "graph": {
      "yAxis": {
         "maxValue": 55,
         "minValue": 15
      },
      "datasequences": [
         {
            "color": "red",
            "datapoints": [
               {
                  "title": "19:42",
                  "value": "23.6"
               },
               {
                  "title": "19:52",
                  "value": "23.5"
               },
               {
                  "title": "20:02",
                  "value": "23.4"
               },
               {
                  "title": "20:12",
                  "value": "23.4"
               },
               {
                  "title": "20:22",
                  "value": "23.3"
               },
               {
                  "title": "20:32",
                  "value": "23.2"
               },
               {
                  "title": "20:42",
                  "value": "23.0"
               },
               {
                  "title": "20:52",
                  "value": "22.9"
               },
               {
                  "title": "21:02",
                  "value": "22.7"
               },
               {
                  "title": "05:10",
                  "value": "24.7"
               },
               {
                  "title": "05:20",
                  "value": "24.7"
               },
               {
                  "title": "05:30",
                  "value": "24.7"
               },
               {
                  "title": "05:40",
                  "value": "24.6"
               }
            ],
            "title": "Temperatura"
         },
         {
            "color": "blue",
            "datapoints": [
               {
                  "title": "19:42",
                  "value": "38.5"
               },
               {
                  "title": "19:52",
                  "value": "38.8"
               },
               {
                  "title": "20:02",
                  "value": "38.3"
               },
               {
                  "title": "20:12",
                  "value": "38.3"
               },
               {
                  "title": "20:22",
                  "value": "38.0"
               },
               {
                  "title": "20:32",
                  "value": "38.0"
               },
               {
                  "title": "20:42",
                  "value": "37.9"
               },
               {
                  "title": "20:52",
                  "value": "38.0"
               },
               {
                  "title": "21:02",
                  "value": "38.3"
               },
               {
                  "title": "05:10",
                  "value": "51.6"
               },
               {
                  "title": "05:20",
                  "value": "51.2"
               },
               {
                  "title": "05:30",
                  "value": "50.9"
               },
               {
                  "title": "05:40",
                  "value": "50.3"
               }
            ],
            "title": "Humedad"
         }
      ],
      "type": "line",
      "title": "Recamara"
   }
}