{
   "graph": {
      "title": "Living",
      "datasequences": [
         {
            "color": "red",
            "title": "Temperatura",
            "datapoints": [
               {
                  "title": "20:00",
                  "value": "25.8"
               },
               {
                  "title": "20:00",
                  "value": "25.8"
               },
               {
                  "title": "20:10",
                  "value": "25.7"
               },
               {
                  "title": "20:20",
                  "value": "25.7"
               },
               {
                  "title": "20:30",
                  "value": "25.7"
               },
               {
                  "title": "20:30",
                  "value": "25.7"
               },
               {
                  "title": "20:40",
                  "value": "25.7"
               },
               {
                  "title": "20:40",
                  "value": "25.7"
               },
               {
                  "title": "20:50",
                  "value": "25.6"
               },
               {
                  "title": "21:00",
                  "value": "25.7"
               },
               {
                  "title": "21:10",
                  "value": "25.9"
               },
               {
                  "title": "21:20",
                  "value": "25.8"
               }
            ]
         },
         {
            "color": "blue",
            "title": "Humedad",
            "datapoints": [
               {
                  "title": "19:50",
                  "value": "36.1"
               },
               {
                  "title": "20:00",
                  "value": "36.3"
               },
               {
                  "title": "20:10",
                  "value": "36.9"
               },
               {
                  "title": "20:20",
                  "value": "37.5"
               },
               {
                  "title": "20:30",
                  "value": "37.5"
               },
               {
                  "title": "20:30",
                  "value": "37.3"
               },
               {
                  "title": "20:40",
                  "value": "37.2"
               },
               {
                  "title": "20:40",
                  "value": "37.4"
               },
               {
                  "title": "20:50",
                  "value": "37.8"
               },
               {
                  "title": "21:00",
                  "value": "37.8"
               },
               {
                  "title": "21:10",
                  "value": "39.0"
               },
               {
                  "title": "21:20",
                  "value": "39.8"
               }
            ]
         }
      ],
      "type": "line",
      "yAxis": {
         "maxValue": 55,
         "minValue": 15
      }
   }
}