{
   "graph": {
      "yAxis": {
         "maxValue": 55,
         "minValue": 10
      },
      "datasequences": [
         {
            "color": "red",
            "datapoints": [
               {
                  "value": "24.30",
                  "title": "18:00"
               },
               {
                  "value": "24.30",
                  "title": "18:10"
               },
               {
                  "value": "24.30",
                  "title": "18:20"
               },
               {
                  "value": "24.30",
                  "title": "18:30"
               },
               {
                  "value": "23.20",
                  "title": "18:40"
               },
               {
                  "value": "23.20",
                  "title": "18:50"
               },
               {
                  "value": "23.20",
                  "title": "19:00"
               },
               {
                  "value": "23.20",
                  "title": "19:10"
               },
               {
                  "value": "22.10",
                  "title": "19:10"
               },
               {
                  "value": "22.10",
                  "title": "19:20"
               },
               {
                  "value": "22.10",
                  "title": "19:30"
               },
               {
                  "value": "22.10",
                  "title": "19:40"
               }
            ],
            "title": "Temperatura"
         },
         {
            "color": "blue",
            "datapoints": [
               {
                  "value": "30.50",
                  "title": "17:50"
               },
               {
                  "value": "29.40",
                  "title": "18:00"
               },
               {
                  "value": "30.50",
                  "title": "18:10"
               },
               {
                  "value": "30.50",
                  "title": "18:20"
               },
               {
                  "value": "30.50",
                  "title": "18:30"
               },
               {
                  "value": "29.40",
                  "title": "18:40"
               },
               {
                  "value": "29.40",
                  "title": "18:50"
               },
               {
                  "value": "28.20",
                  "title": "19:00"
               },
               {
                  "value": "28.20",
                  "title": "19:10"
               },
               {
                  "value": "28.20",
                  "title": "19:20"
               },
               {
                  "value": "28.20",
                  "title": "19:30"
               },
               {
                  "value": "28.20",
                  "title": "19:40"
               }
            ],
            "title": "Humedad"
         }
      ],
      "type": "line",
      "title": "Balcon"
   }
}