{
   "graph": {
      "yAxis": {
         "maxValue": 55,
         "minValue": 15
      },
      "datasequences": [
         {
            "color": "red",
            "datapoints": [
               {
                  "title": "02:40",
                  "value": "27.14"
               },
               {
                  "title": "02:50",
                  "value": "27.1"
               },
               {
                  "title": "02:50",
                  "value": "27.1"
               },
               {
                  "title": "03:00",
                  "value": "26.89"
               },
               {
                  "title": "03:10",
                  "value": "26.77"
               },
               {
                  "title": "03:20",
                  "value": "26.74"
               },
               {
                  "title": "03:30",
                  "value": "26.55"
               },
               {
                  "title": "03:30",
                  "value": "26.59"
               },
               {
                  "title": "03:40",
                  "value": "26.6"
               },
               {
                  "title": "03:40",
                  "value": "26.6"
               },
               {
                  "title": "03:50",
                  "value": "26.58"
               },
               {
                  "title": "03:50",
                  "value": "26.63"
               }
            ],
            "title": "Temperatura"
         },
         {
            "color": "blue",
            "datapoints": [
               {
                  "title": "02:40",
                  "value": "941.79"
               },
               {
                  "title": "02:50",
                  "value": "941.82"
               },
               {
                  "title": "02:50",
                  "value": "941.84"
               },
               {
                  "title": "03:00",
                  "value": "941.75"
               },
               {
                  "title": "03:10",
                  "value": "941.67"
               },
               {
                  "title": "03:20",
                  "value": "941.59"
               },
               {
                  "title": "03:30",
                  "value": "941.61"
               },
               {
                  "title": "03:30",
                  "value": "941.55"
               },
               {
                  "title": "03:40",
                  "value": "941.41"
               },
               {
                  "title": "03:40",
                  "value": "941.39"
               },
               {
                  "title": "03:50",
                  "value": "941.33"
               },
               {
                  "title": "03:50",
                  "value": "941.39"
               }
            ],
            "title": "Presion"
         }
      ],
      "type": "line",
      "title": "Balcon"
   }
}