{
   "graph": {
      "title": "Balcon",
      "datasequences": [
         {
            "color": "red",
            "title": "Temperatura",
            "datapoints": [
               {
                  "title": "14:40",
                  "value": "29.0"
               },
               {
                  "title": "14:40",
                  "value": "28.9"
               },
               {
                  "title": "14:50",
                  "value": "28.8"
               },
               {
                  "title": "15:00",
                  "value": "28.8"
               },
               {
                  "title": "15:10",
                  "value": "28.2"
               },
               {
                  "title": "15:20",
                  "value": "27.6"
               },
               {
                  "title": "15:30",
                  "value": "27.6"
               },
               {
                  "title": "15:40",
                  "value": "27.8"
               },
               {
                  "title": "15:50",
                  "value": "28.5"
               },
               {
                  "title": "16:00",
                  "value": "27.7"
               },
               {
                  "title": "16:10",
                  "value": "27.6"
               },
               {
                  "title": "16:20",
                  "value": "27.3"
               }
            ]
         },
         {
            "color": "blue",
            "title": "Humedad",
            "datapoints": [
               {
                  "title": "14:30",
                  "value": "23.4"
               },
               {
                  "title": "14:40",
                  "value": "23.8"
               },
               {
                  "title": "14:50",
                  "value": "24.6"
               },
               {
                  "title": "15:00",
                  "value": "24.1"
               },
               {
                  "title": "15:10",
                  "value": "24.4"
               },
               {
                  "title": "15:20",
                  "value": "24.3"
               },
               {
                  "title": "15:30",
                  "value": "24.1"
               },
               {
                  "title": "15:40",
                  "value": "23.5"
               },
               {
                  "title": "15:50",
                  "value": "22.8"
               },
               {
                  "title": "16:00",
                  "value": "22.6"
               },
               {
                  "title": "16:10",
                  "value": "23.6"
               },
               {
                  "title": "16:20",
                  "value": "23.7"
               }
            ]
         }
      ],
      "type": "line",
      "yAxis": {
         "maxValue": 55,
         "minValue": 10
      }
   }
}