{
   "graph": {
      "yAxis": {
         "maxValue": 55,
         "minValue": 15
      },
      "datasequences": [
         {
            "color": "red",
            "datapoints": [
               {
                  "title": "02:10",
                  "value": "23.6"
               },
               {
                  "title": "02:20",
                  "value": "23.6"
               },
               {
                  "title": "02:30",
                  "value": "23.6"
               },
               {
                  "title": "02:40",
                  "value": "23.6"
               },
               {
                  "title": "02:50",
                  "value": "23.6"
               },
               {
                  "title": "03:00",
                  "value": "23.6"
               },
               {
                  "title": "03:10",
                  "value": "23.6"
               },
               {
                  "title": "03:20",
                  "value": "23.6"
               },
               {
                  "title": "03:31",
                  "value": "23.6"
               },
               {
                  "title": "03:41",
                  "value": "23.6"
               },
               {
                  "title": "04:01",
                  "value": "23.6"
               },
               {
                  "title": "04:11",
                  "value": "23.5"
               },
               {
                  "title": "04:21",
                  "value": "23.5"
               }
            ],
            "title": "Temperatura"
         },
         {
            "color": "blue",
            "datapoints": [
               {
                  "title": "02:10",
                  "value": "45.5"
               },
               {
                  "title": "02:20",
                  "value": "45.3"
               },
               {
                  "title": "02:30",
                  "value": "45.4"
               },
               {
                  "title": "02:40",
                  "value": "45.5"
               },
               {
                  "title": "02:50",
                  "value": "45.9"
               },
               {
                  "title": "03:00",
                  "value": "46.8"
               },
               {
                  "title": "03:10",
                  "value": "46.9"
               },
               {
                  "title": "03:20",
                  "value": "47.3"
               },
               {
                  "title": "03:31",
                  "value": "48.3"
               },
               {
                  "title": "03:41",
                  "value": "47.7"
               },
               {
                  "title": "04:01",
                  "value": "47.7"
               },
               {
                  "title": "04:11",
                  "value": "47.8"
               },
               {
                  "title": "04:21",
                  "value": "47.8"
               }
            ],
            "title": "Humedad"
         }
      ],
      "type": "line",
      "title": "Recamara"
   }
}