{
   "graph": {
      "yAxis": {
         "maxValue": 55,
         "minValue": 15
      },
      "datasequences": [
         {
            "color": "red",
            "datapoints": [
               {
                  "title": "07:40",
                  "value": "21.35"
               },
               {
                  "title": "07:50",
                  "value": "21.46"
               },
               {
                  "title": "08:00",
                  "value": "21.27"
               },
               {
                  "title": "08:10",
                  "value": "21.37"
               },
               {
                  "title": "08:10",
                  "value": "21.33"
               },
               {
                  "title": "08:20",
                  "value": "21.44"
               },
               {
                  "title": "08:30",
                  "value": "21.75"
               },
               {
                  "title": "08:40",
                  "value": "21.87"
               },
               {
                  "title": "08:50",
                  "value": "22.02"
               },
               {
                  "title": "08:50",
                  "value": "22.06"
               },
               {
                  "title": "09:00",
                  "value": "22.3"
               },
               {
                  "title": "09:10",
                  "value": "22.23"
               }
            ],
            "title": "Temperatura"
         },
         {
            "color": "blue",
            "datapoints": [
               {
                  "title": "07:30",
                  "value": "946.4"
               },
               {
                  "title": "07:40",
                  "value": "946.41"
               },
               {
                  "title": "07:50",
                  "value": "946.6"
               },
               {
                  "title": "08:00",
                  "value": "946.77"
               },
               {
                  "title": "08:10",
                  "value": "946.77"
               },
               {
                  "title": "08:10",
                  "value": "946.7"
               },
               {
                  "title": "08:20",
                  "value": "946.65"
               },
               {
                  "title": "08:30",
                  "value": "946.75"
               },
               {
                  "title": "08:40",
                  "value": "946.69"
               },
               {
                  "title": "08:50",
                  "value": "946.79"
               },
               {
                  "title": "09:00",
                  "value": "946.88"
               },
               {
                  "title": "09:10",
                  "value": "946.93"
               }
            ],
            "title": "Presion"
         }
      ],
      "type": "line",
      "title": "Balcon"
   }
}