{
   "graph": {
      "title": "Recamara",
      "datasequences": [
         {
            "color": "red",
            "title": "Temperatura",
            "datapoints": [
               {
                  "value": "20.9",
                  "title": "10:02"
               },
               {
                  "value": "21.0",
                  "title": "10:12"
               },
               {
                  "value": "21.1",
                  "title": "10:23"
               },
               {
                  "value": "21.1",
                  "title": "10:33"
               },
               {
                  "value": "21.3",
                  "title": "10:43"
               },
               {
                  "value": "21.5",
                  "title": "10:53"
               },
               {
                  "value": "21.8",
                  "title": "11:03"
               },
               {
                  "value": "21.2",
                  "title": "05:03"
               },
               {
                  "value": "20.0",
                  "title": "07:30"
               },
               {
                  "value": "20.4",
                  "title": "07:40"
               },
               {
                  "value": "21.5",
                  "title": "07:50"
               },
               {
                  "value": "22.1",
                  "title": "08:00"
               },
               {
                  "value": "22.4",
                  "title": "08:10"
               }
            ]
         },
         {
            "color": "blue",
            "title": "Humedad",
            "datapoints": [
               {
                  "value": "36.2",
                  "title": "10:02"
               },
               {
                  "value": "35.7",
                  "title": "10:12"
               },
               {
                  "value": "35.8",
                  "title": "10:23"
               },
               {
                  "value": "35.3",
                  "title": "10:33"
               },
               {
                  "value": "35.3",
                  "title": "10:43"
               },
               {
                  "value": "35.1",
                  "title": "10:53"
               },
               {
                  "value": "34.3",
                  "title": "11:03"
               },
               {
                  "value": "44.6",
                  "title": "05:03"
               },
               {
                  "value": "43.9",
                  "title": "07:30"
               },
               {
                  "value": "42.9",
                  "title": "07:40"
               },
               {
                  "value": "41.4",
                  "title": "07:50"
               },
               {
                  "value": "40.8",
                  "title": "08:00"
               },
               {
                  "value": "40.5",
                  "title": "08:10"
               }
            ]
         }
      ],
      "type": "line",
      "yAxis": {
         "minValue": 15
      }
   }
}