{
   "graph": {
      "yAxis": {
         "maxValue": 55,
         "minValue": 15
      },
      "datasequences": [
         {
            "color": "red",
            "datapoints": [
               {
                  "title": "09:12",
                  "value": "26.2"
               },
               {
                  "title": "09:22",
                  "value": "26.2"
               },
               {
                  "title": "09:32",
                  "value": "26.2"
               },
               {
                  "title": "09:42",
                  "value": "26.2"
               },
               {
                  "title": "09:52",
                  "value": "26.2"
               },
               {
                  "title": "10:02",
                  "value": "26.3"
               },
               {
                  "title": "10:12",
                  "value": "26.3"
               },
               {
                  "title": "10:22",
                  "value": "26.4"
               },
               {
                  "title": "10:32",
                  "value": "26.4"
               },
               {
                  "title": "10:42",
                  "value": "26.4"
               },
               {
                  "title": "10:52",
                  "value": "26.5"
               },
               {
                  "title": "03:50",
                  "value": "28.1"
               },
               {
                  "title": "04:10",
                  "value": "28.0"
               }
            ],
            "title": "Temperatura"
         },
         {
            "color": "blue",
            "datapoints": [
               {
                  "title": "09:12",
                  "value": "34.0"
               },
               {
                  "title": "09:22",
                  "value": "33.9"
               },
               {
                  "title": "09:32",
                  "value": "33.5"
               },
               {
                  "title": "09:42",
                  "value": "33.0"
               },
               {
                  "title": "09:52",
                  "value": "32.6"
               },
               {
                  "title": "10:02",
                  "value": "32.7"
               },
               {
                  "title": "10:12",
                  "value": "33.4"
               },
               {
                  "title": "10:22",
                  "value": "33.3"
               },
               {
                  "title": "10:32",
                  "value": "33.2"
               },
               {
                  "title": "10:42",
                  "value": "33.4"
               },
               {
                  "title": "10:52",
                  "value": "33.1"
               },
               {
                  "title": "03:50",
                  "value": "30.6"
               },
               {
                  "title": "04:10",
                  "value": "30.5"
               }
            ],
            "title": "Humedad"
         }
      ],
      "type": "line",
      "title": "Recamara"
   }
}