{
   "graph": {
      "title": "Balcon",
      "datasequences": [
         {
            "color": "red",
            "title": "Temperatura",
            "datapoints": [
               {
                  "value": "15.10",
                  "title": "01:30"
               },
               {
                  "value": "15.10",
                  "title": "01:40"
               },
               {
                  "value": "14.00",
                  "title": "01:50"
               },
               {
                  "value": "14.00",
                  "title": "02:00"
               },
               {
                  "value": "14.00",
                  "title": "02:10"
               },
               {
                  "value": "14.00",
                  "title": "02:20"
               },
               {
                  "value": "14.00",
                  "title": "02:30"
               },
               {
                  "value": "14.00",
                  "title": "02:40"
               },
               {
                  "value": "14.00",
                  "title": "02:50"
               },
               {
                  "value": "15.10",
                  "title": "03:00"
               },
               {
                  "value": "15.10",
                  "title": "03:10"
               },
               {
                  "value": "15.10",
                  "title": "03:20"
               }
            ]
         },
         {
            "color": "blue",
            "title": "Humedad",
            "datapoints": [
               {
                  "value": "62.30",
                  "title": "01:30"
               },
               {
                  "value": "61.50",
                  "title": "01:40"
               },
               {
                  "value": "63.80",
                  "title": "01:50"
               },
               {
                  "value": "62.80",
                  "title": "02:00"
               },
               {
                  "value": "62.80",
                  "title": "02:10"
               },
               {
                  "value": "62.80",
                  "title": "02:20"
               },
               {
                  "value": "63.30",
                  "title": "02:30"
               },
               {
                  "value": "62.20",
                  "title": "02:40"
               },
               {
                  "value": "61.10",
                  "title": "02:50"
               },
               {
                  "value": "61.20",
                  "title": "03:00"
               },
               {
                  "value": "61.20",
                  "title": "03:10"
               },
               {
                  "value": "60.80",
                  "title": "03:20"
               }
            ]
         }
      ],
      "type": "line",
      "yAxis": {
         "maxValue": 55,
         "minValue": 10
      }
   }
}