{
   "graph": {
      "yAxis": {
         "maxValue": 55,
         "minValue": 15
      },
      "datasequences": [
         {
            "color": "red",
            "datapoints": [
               {
                  "value": "26.2",
                  "title": "12:00"
               },
               {
                  "value": "26.3",
                  "title": "12:00"
               },
               {
                  "value": "26.6",
                  "title": "12:00"
               },
               {
                  "value": "26.8",
                  "title": "12:00"
               },
               {
                  "value": "27.0",
                  "title": "12:00"
               },
               {
                  "value": "27.1",
                  "title": "13:00"
               },
               {
                  "value": "27.2",
                  "title": "13:00"
               },
               {
                  "value": "27.4",
                  "title": "13:00"
               },
               {
                  "value": "27.7",
                  "title": "13:00"
               },
               {
                  "value": "27.9",
                  "title": "13:00"
               },
               {
                  "value": "28.0",
                  "title": "13:00"
               },
               {
                  "value": "28.2",
                  "title": "14:00"
               },
               {
                  "value": "28.4",
                  "title": "14:00"
               }
            ],
            "title": "Temperatura"
         },
         {
            "color": "blue",
            "datapoints": [
               {
                  "value": "41.1",
                  "title": "12:00"
               },
               {
                  "value": "39.6",
                  "title": "12:00"
               },
               {
                  "value": "39.8",
                  "title": "12:00"
               },
               {
                  "value": "38.8",
                  "title": "12:00"
               },
               {
                  "value": "38.5",
                  "title": "12:00"
               },
               {
                  "value": "37.7",
                  "title": "13:00"
               },
               {
                  "value": "37.1",
                  "title": "13:00"
               },
               {
                  "value": "36.2",
                  "title": "13:00"
               },
               {
                  "value": "36.2",
                  "title": "13:00"
               },
               {
                  "value": "36.2",
                  "title": "13:00"
               },
               {
                  "value": "35.1",
                  "title": "13:00"
               },
               {
                  "value": "35.2",
                  "title": "14:00"
               },
               {
                  "value": "35.6",
                  "title": "14:00"
               }
            ],
            "title": "Humedad"
         }
      ],
      "type": "line",
      "title": "Recamara"
   }
}