{
   "graph": {
      "title": "Recamara",
      "datasequences": [
         {
            "color": "red",
            "title": "Temperatura",
            "datapoints": [
               {
                  "value": "24.1",
                  "title": "14:10"
               },
               {
                  "value": "24.2",
                  "title": "14:20"
               },
               {
                  "value": "24.1",
                  "title": "14:30"
               },
               {
                  "value": "24.2",
                  "title": "14:40"
               },
               {
                  "value": "24.2",
                  "title": "14:50"
               },
               {
                  "value": "24.1",
                  "title": "15:00"
               },
               {
                  "value": "24.2",
                  "title": "15:10"
               },
               {
                  "value": "23.9",
                  "title": "15:20"
               },
               {
                  "value": "23.5",
                  "title": "15:30"
               },
               {
                  "value": "23.2",
                  "title": "15:40"
               },
               {
                  "value": "23.0",
                  "title": "15:50"
               },
               {
                  "value": "22.8",
                  "title": "16:00"
               },
               {
                  "value": "22.7",
                  "title": "16:10"
               }
            ]
         },
         {
            "color": "blue",
            "title": "Humedad",
            "datapoints": [
               {
                  "value": "38.2",
                  "title": "14:10"
               },
               {
                  "value": "38.1",
                  "title": "14:20"
               },
               {
                  "value": "38.9",
                  "title": "14:30"
               },
               {
                  "value": "38.4",
                  "title": "14:40"
               },
               {
                  "value": "38.4",
                  "title": "14:50"
               },
               {
                  "value": "38.1",
                  "title": "15:00"
               },
               {
                  "value": "37.9",
                  "title": "15:10"
               },
               {
                  "value": "37.9",
                  "title": "15:20"
               },
               {
                  "value": "38.3",
                  "title": "15:30"
               },
               {
                  "value": "38.5",
                  "title": "15:40"
               },
               {
                  "value": "38.7",
                  "title": "15:50"
               },
               {
                  "value": "38.7",
                  "title": "16:00"
               },
               {
                  "value": "39.1",
                  "title": "16:10"
               }
            ]
         }
      ],
      "type": "line",
      "yAxis": {
         "minValue": 15
      }
   }
}