{
   "graph": {
      "yAxis": {
         "maxValue": 55,
         "minValue": 15
      },
      "datasequences": [
         {
            "color": "red",
            "datapoints": [
               {
                  "title": "20:20",
                  "value": "27.32"
               },
               {
                  "title": "20:30",
                  "value": "26.87"
               },
               {
                  "title": "20:40",
                  "value": "26.39"
               },
               {
                  "title": "20:50",
                  "value": "26.46"
               },
               {
                  "title": "21:00",
                  "value": "25.93"
               },
               {
                  "title": "21:00",
                  "value": "25.93"
               },
               {
                  "title": "21:10",
                  "value": "26.01"
               },
               {
                  "title": "21:10",
                  "value": "25.94"
               },
               {
                  "title": "21:20",
                  "value": "26.03"
               },
               {
                  "title": "21:30",
                  "value": "25.62"
               },
               {
                  "title": "21:40",
                  "value": "25.45"
               },
               {
                  "title": "21:50",
                  "value": "25.41"
               },
               {
                  "title": "21:50",
                  "value": "25.4"
               }
            ],
            "title": "Temperatura"
         },
         {
            "color": "blue",
            "datapoints": [
               {
                  "title": "20:10",
                  "value": "942.96"
               },
               {
                  "title": "20:20",
                  "value": "943.08"
               },
               {
                  "title": "20:30",
                  "value": "943.25"
               },
               {
                  "title": "20:40",
                  "value": "943.4"
               },
               {
                  "title": "20:50",
                  "value": "943.56"
               },
               {
                  "title": "21:00",
                  "value": "943.73"
               },
               {
                  "title": "21:10",
                  "value": "943.82"
               },
               {
                  "title": "21:20",
                  "value": "943.9"
               },
               {
                  "title": "21:30",
                  "value": "943.98"
               },
               {
                  "title": "21:40",
                  "value": "944.1"
               },
               {
                  "title": "21:50",
                  "value": "944.11"
               }
            ],
            "title": "Presion"
         }
      ],
      "type": "line",
      "title": "Balcon"
   }
}