{
   "graph": {
      "yAxis": {
         "maxValue": 55,
         "minValue": 15
      },
      "datasequences": [
         {
            "color": "red",
            "datapoints": [
               {
                  "title": "23:30",
                  "value": "28.55"
               },
               {
                  "title": "23:40",
                  "value": "28.57"
               },
               {
                  "title": "23:50",
                  "value": "28.47"
               },
               {
                  "title": "00:00",
                  "value": "28.56"
               },
               {
                  "title": "00:00",
                  "value": "28.6"
               },
               {
                  "title": "00:10",
                  "value": "28.52"
               },
               {
                  "title": "00:20",
                  "value": "28.49"
               },
               {
                  "title": "00:20",
                  "value": "28.44"
               },
               {
                  "title": "00:30",
                  "value": "28.38"
               },
               {
                  "title": "00:40",
                  "value": "28.49"
               },
               {
                  "title": "00:40",
                  "value": "28.5"
               },
               {
                  "title": "00:50",
                  "value": "28.4"
               }
            ],
            "title": "Temperatura"
         },
         {
            "color": "blue",
            "datapoints": [
               {
                  "title": "23:20",
                  "value": "942.52"
               },
               {
                  "title": "23:30",
                  "value": "942.36"
               },
               {
                  "title": "23:40",
                  "value": "942.29"
               },
               {
                  "title": "23:50",
                  "value": "942.27"
               },
               {
                  "title": "00:00",
                  "value": "942.24"
               },
               {
                  "title": "00:00",
                  "value": "942.24"
               },
               {
                  "title": "00:10",
                  "value": "942.18"
               },
               {
                  "title": "00:20",
                  "value": "942.13"
               },
               {
                  "title": "00:30",
                  "value": "942.04"
               },
               {
                  "title": "00:40",
                  "value": "942.04"
               },
               {
                  "title": "00:40",
                  "value": "942.06"
               },
               {
                  "title": "00:50",
                  "value": "942.02"
               }
            ],
            "title": "Presion"
         }
      ],
      "type": "line",
      "title": "Balcon"
   }
}